cdp_client/__init__.py
cdp_client/cdp.py
cdp_client/cdp_pb2.py
cdp_client/tests/__init__.py
cdp_client/tests/fake_data.py
cdp_client/tests/test_client.py
cdp_client/tests/test_connection.py
cdp_client/tests/test_main.py
cdp_client/tests/test_node.py
cdp_client/tests/test_nodetree.py
cdp_client/tests/test_requests.py
cdp_client-2.2.2.dist-info/LICENSE.txt
cdp_client-2.2.2.dist-info/METADATA
cdp_client-2.2.2.dist-info/WHEEL
cdp_client-2.2.2.dist-info/top_level.txt
cdp_client-2.2.2.dist-info/RECORD
