Metadata-Version: 2.1
Name: cdp-client
Version: 2.2.2
Summary: Provides an API that allows to interact with CDP applications
Home-page: https://github.com/CDPTechnologies/PythonCDPClient
Author: CDP Technologies AS
Author-email: info@cdptech.com
License: MIT
Keywords: cdp cdpstudio studio client cdp-client cdp_client
Classifier: Development Status :: 5 - Production/Stable
Classifier: Environment :: Console
Classifier: Intended Audience :: Developers
Classifier: License :: OSI Approved :: MIT License
Classifier: Operating System :: OS Independent
Classifier: Topic :: Software Development
Classifier: Programming Language :: Python :: 3
Classifier: Programming Language :: Python :: 3.8
Classifier: Programming Language :: Python :: 3.9
Classifier: Programming Language :: Python :: 3.10
Classifier: Programming Language :: Python :: 3.11
Requires-Python: >=3.8
License-File: LICENSE.txt
Requires-Dist: promise
Requires-Dist: websocket-client <=0.56.0
Requires-Dist: protobuf <=3.20.0
Requires-Dist: mock
